quart_csrf/__init__.py
quart_csrf/csrf.py
quart_csrf-0.2.dist-info/LICENSE
quart_csrf-0.2.dist-info/METADATA
quart_csrf-0.2.dist-info/WHEEL
quart_csrf-0.2.dist-info/top_level.txt
quart_csrf-0.2.dist-info/RECORD
