Metadata-Version: 2.1
Name: quart-csrf
Version: 0.2
Summary: Quart CSRF Protection
Home-page: https://gitlab.com/wcorrales/quart-csrf
Author: Wagner Corrales
Author-email: wagnerc4@gmail.com
License: MIT
Platform: UNKNOWN
Classifier: Development Status :: 3 - Alpha
Classifier: Environment :: Web Environment
Classifier: Intended Audience :: Developers
Classifier: License :: OSI Approved :: MIT License
Classifier: Operating System :: OS Independent
Classifier: Programming Language :: Python
Classifier: Programming Language :: Python :: 3
Classifier: Programming Language :: Python :: 3.7
Classifier: Programming Language :: Python :: 3.8
Classifier: Topic :: Internet :: WWW/HTTP :: Dynamic Content
Classifier: Topic :: Software Development :: Libraries :: Python Modules
Requires-Python: >=3.7
Requires-Dist: itsdangerous
Requires-Dist: quart
Requires-Dist: wtforms
